preschoollib/__init__.py
preschoollib/myfunctions.py
preschoollib-0.1.0.dist-info/METADATA
preschoollib-0.1.0.dist-info/WHEEL
preschoollib-0.1.0.dist-info/top_level.txt
preschoollib-0.1.0.dist-info/RECORD
