Metadata-Version: 2.1
Name: preschoollib
Version: 0.1.0
Summary: My first Python library
Author: Priya
License: MIT
Platform: UNKNOWN
